tkmatrix/__init__.py
tkmatrix/__main__.py
tkmatrix/inject_model.py
tkmatrix/inject_rv_model.py
tkmatrix/programmatic.py
tkmatrix/properties.yaml
tkmatrix/rv.py
tkmatrix/tkmatrix_class.py
tkmatrix/custom_algorithms/BlsCustomSearchAlgorithm.py
tkmatrix/custom_algorithms/__init__.py
tkmatrix/custom_algorithms/custom_search.py
tkmatrix/tests/__init__.py
tkmatrix/tests/test_tkmatrix.py
tkmatrix-0.11.1.dist-info/LICENSE
tkmatrix-0.11.1.dist-info/METADATA
tkmatrix-0.11.1.dist-info/WHEEL
tkmatrix-0.11.1.dist-info/top_level.txt
tkmatrix-0.11.1.dist-info/RECORD
