Metadata-Version: 2.1
Name: tkmatrix
Version: 0.11.1
Summary: ToolKit for Multi-phAse Transits Recovery from Injected eXoplanets
Home-page: https://github.com/PlanetHunters/tkmatrix
Author: M. Dévora-Pajares & F.J. Pozuelos
Author-email: mdevorapajares@protonmail.com
License: UNKNOWN
Platform: UNKNOWN
Classifier: Programming Language :: Python :: 3
Classifier: License :: OSI Approved :: MIT License
Classifier: Operating System :: OS Independent
Requires-Python: >=3.10
Requires-Dist: argparse ==1.4.0
Requires-Dist: beautifulsoup4 ==4.9.3
Requires-Dist: configparser ==5.0.1
Requires-Dist: corner ==2.1.0
Requires-Dist: ellc ==1.8.5
Requires-Dist: lcbuilder ==0.18.3
Requires-Dist: mock ==4.0.3
Requires-Dist: pyparsing ==2.4.7
Requires-Dist: seaborn ==0.11.1
Requires-Dist: setuptools >=41.0.0
Requires-Dist: sklearn ==0.0
